climate_analysis/__init__.py
climate_analysis/maps.py
climate_analysis/time_series.py
forecast-backend/utils.py
tests/test_maps.py
tests/test_time_series.py
climate_analysis-0.1.11.dist-info/LICENSE
climate_analysis-0.1.11.dist-info/METADATA
climate_analysis-0.1.11.dist-info/WHEEL
climate_analysis-0.1.11.dist-info/entry_points.txt
climate_analysis-0.1.11.dist-info/top_level.txt
climate_analysis-0.1.11.dist-info/RECORD
