Metadata-Version: 2.2
Name: climate_analysis
Version: 0.1.11
Summary: The Climate Analysis Package is a powerful tool designed for analyzing climate data with a focus on generating time-series visualizations and map-based insights.
Author: Bijan Fallah
Author-email: Bijan Fallah <bijan.fallah@gmail.com>
License: MIT License
Keywords: climate,python,package
Classifier: Development Status :: 4 - Beta
Classifier: Intended Audience :: Developers
Classifier: License :: OSI Approved :: MIT License
Classifier: Programming Language :: Python :: 3
Classifier: Programming Language :: Python :: 3.7
Classifier: Programming Language :: Python :: 3.8
Classifier: Programming Language :: Python :: 3.9
Classifier: Programming Language :: Python :: 3.10
Requires-Python: >=3.7
License-File: LICENSE
Requires-Dist: numpy<1.25,>=1.22.0
Requires-Dist: pandas>=1.4.0
Provides-Extra: dev
Requires-Dist: pytest>=6.0; extra == "dev"
Requires-Dist: black>=23.0; extra == "dev"
Requires-Dist: flake8>=4.0; extra == "dev"
Dynamic: author
